<?xml version="1.0"?>
<instance entity-name="altera_fir_compiler_ii" version="13.1" >
<generic name="deviceFamily" value="Cyclone V" />
<generic name="filterType" value="Single Rate" />
<generic name="interpFactor" value="1" />
<generic name="decimFactor" value="1" />
<generic name="L_bandsFilter" value="All taps" />
<generic name="clockRate" value="50" />
<generic name="clockSlack" value="0" />
<generic name="speedGrade" value="Medium" />
<generic name="coeffReload" value="false" />
<generic name="baseAddress" value="0" />
<generic name="readWriteMode" value="Read/Write" />
<generic name="backPressure" value="false" />
<generic name="symmetryMode" value="Non Symmetry" />
<generic name="delayRAMBlockThreshold" value="20" />
<generic name="dualMemDistRAMThreshold" value="1280" />
<generic name="mRAMThreshold" value="1000000" />
<generic name="hardMultiplierThreshold" value="-1" />
<generic name="inputRate" value="50" />
<generic name="inputChannelNum" value="1" />
<generic name="inputType" value="Signed Binary" />
<generic name="inputBitWidth" value="14" />
<generic name="inputFracBitWidth" value="0" />
<generic name="coeffSetRealValue" value="1.124018E-4,1.79667E-4,3.160804E-4,5.131643E-4,7.861857E-4,0.00115153,0.001626182,0.002227091,0.00297042,0.003870724,0.004940077,0.006187194,0.007616591,0.009227829,0.01101489,0.01296573,0.01506202,0.01727922,0.01958675,0.02194863,0.02432419,0.0266692,0.02893707,0.0310803,0.03305198,0.03480741,0.03630557,0.03751068,0.0383934,0.03893197,0.039113,0.03893197,0.0383934,0.03751068,0.03630557,0.03480741,0.03305198,0.0310803,0.02893707,0.0266692,0.02432419,0.02194863,0.01958675,0.01727922,0.01506202,0.01296573,0.01101489,0.009227829,0.007616591,0.006187194,0.004940077,0.003870724,0.00297042,0.002227091,0.001626182,0.00115153,7.861857E-4,5.131643E-4,3.160804E-4,1.79667E-4" />
<generic name="coeffType" value="Signed Binary" />
<generic name="coeffScaling" value="Auto" />
<generic name="coeffBitWidth" value="12" />
<generic name="coeffFracBitWidth" value="0" />
<generic name="outType" value="Signed Binary" />
<generic name="outMSBRound" value="Truncation" />
<generic name="outMsbBitRem" value="0" />
<generic name="outLSBRound" value="Truncation" />
<generic name="outLsbBitRem" value="0" />
<generic name="resoureEstimation" value="1000,1200,10" />
<generic name="bankCount" value="1" />
<generic name="bankDisplay" value="0" />
</instance>
